hyyshare/__init__.py
hyyshare/__main__.py
hyyshare/cleanup.py
hyyshare/cli.py
hyyshare/config.py
hyyshare/handler.py
hyyshare/security.py
hyyshare/server.py
hyyshare/setup.py
hyyshare/user_manager.py
hyyshare/utils.py
hyyshare/version.py
hyyshare-2025.7.27.dist-info/licenses/LICENSE.txt
hyyshare-2025.7.27.dist-info/METADATA
hyyshare-2025.7.27.dist-info/WHEEL
hyyshare-2025.7.27.dist-info/entry_points.txt
hyyshare-2025.7.27.dist-info/top_level.txt
hyyshare-2025.7.27.dist-info/RECORD
